api/__init__.py
api/orders_api.py
api/payment_links_api.py
api/payments_api.py
api/refunds_api.py
api/settlements_api.py
api/token_vault_api.py
interface/__init__.py
interface/cfconfig.py
interface/cferror.py
interface/cfheaders.py
interface/gatewayinterface.py
models/__init__.py
models/cf_app.py
models/cf_app_payment.py
models/cf_authorization_in_payments_entity.py
models/cf_authorization_request.py
models/cf_card.py
models/cf_card_emi.py
models/cf_card_payment.py
models/cf_cardless_emi.py
models/cf_cardless_emi_payment.py
models/cf_cryptogram.py
models/cf_customer_details.py
models/cf_error.py
models/cf_fetch_all_saved_instruments.py
models/cf_link.py
models/cf_link_cancelled_response.py
models/cf_link_customer_details_entity.py
models/cf_link_meta_entity.py
models/cf_link_notify_entity.py
models/cf_link_orders.py
models/cf_link_request.py
models/cf_netbanking.py
models/cf_netbanking_payment.py
models/cf_order.py
models/cf_order_meta.py
models/cf_order_pay_data.py
models/cf_order_pay_request.py
models/cf_order_pay_response.py
models/cf_order_request.py
models/cf_paylater.py
models/cf_paylater_payment.py
models/cf_payment_method.py
models/cf_payment_url_object.py
models/cf_payments_entity.py
models/cf_payments_entity_app.py
models/cf_payments_entity_app_payment.py
models/cf_payments_entity_card.py
models/cf_payments_entity_card_payment.py
models/cf_payments_entity_cardless_emi.py
models/cf_payments_entity_cardless_emi_payment.py
models/cf_payments_entity_method.py
models/cf_payments_entity_netbanking_payment.py
models/cf_payments_entity_paylater.py
models/cf_payments_entity_paylater_payment.py
models/cf_payments_entity_upi.py
models/cf_payments_entity_upi_payment.py
models/cf_refund.py
models/cf_refund_request.py
models/cf_refund_url_object.py
models/cf_saved_instrument_meta.py
models/cf_settlement_url_object.py
models/cf_settlements_entity.py
models/cf_vendor_split.py
models/cfemi_payment.py
models/cfupi.py
models/cfupi_authorize_details.py
cashfree_pg_sdk_python-2.0.1.dist-info/LICENSE.txt
cashfree_pg_sdk_python-2.0.1.dist-info/METADATA
cashfree_pg_sdk_python-2.0.1.dist-info/WHEEL
cashfree_pg_sdk_python-2.0.1.dist-info/top_level.txt
cashfree_pg_sdk_python-2.0.1.dist-info/RECORD
