Metadata-Version: 2.1
Name: cashfree-pg-sdk-python
Version: 2.0.1
Summary: Casfree Payments Payment Gateway Python SDK
Home-page: https://github.com/cashfree/cashfree-pg-sdk-python
Author: Cashfree Payments
Author-email: developers@cashfree.com
License: MIT
Keywords: pg-sdk,cashfree-pg-sdk,cashfree,cashfree-python
License-File: LICENSE.txt
Requires-Dist: six (>=1.10)
Requires-Dist: python-dateutil
